django_resurrected/__init__.py
django_resurrected/collectors.py
django_resurrected/constants.py
django_resurrected/managers.py
django_resurrected/models.py
django_resurrected/py.typed
django_resurrected-0.4.0.dist-info/METADATA
django_resurrected-0.4.0.dist-info/WHEEL
django_resurrected-0.4.0.dist-info/RECORD
