Metadata-Version: 2.4
Name: django-resurrected
Version: 0.4.0
Summary: Soft-delete functionality for Django projects with relationship-aware deletion and restoration.
Project-URL: Repository, https://github.com/krzysiek951/django-resurrected
Author-email: Krzysztof Czopkiewicz <krzysiek951@gmail.com>
License-Expression: MIT
Keywords: recovery,restore,resurrect,retention,soft-delete,softdelete,trash,undelete
Classifier: Development Status :: 4 - Beta
Classifier: Framework :: Django
Classifier: Framework :: Django :: 4.2
Classifier: Framework :: Django :: 5.0
Classifier: Framework :: Django :: 5.1
Classifier: Framework :: Django :: 5.2
Classifier: Programming Language :: Python
Classifier: Programming Language :: Python :: 3 :: Only
Classifier: Programming Language :: Python :: 3.9
Classifier: Programming Language :: Python :: 3.10
Classifier: Programming Language :: Python :: 3.11
Classifier: Programming Language :: Python :: 3.12
Classifier: Programming Language :: Python :: 3.13
Requires-Python: >=3.9
Requires-Dist: django>=4.2
